src/__init__.py
src/plugins/__init__.py
src/plugins/ELFChatBot/__init__.py
src/plugins/ELFChatBot/config.py
src/plugins/ELFChatBot/plugins/ELF_bot.py
src/plugins/ELFChatBot/plugins/Random_bot.py
src/plugins/ELFChatBot/plugins/__init__.py
src/plugins/ELFChatBot/plugins/single_session.py
src/plugins/ELFChatBot/plugins/ChatBotApi/__init__.py
src/plugins/ELFChatBot/plugins/ChatBotApi/baiduBot.py
src/plugins/ELFChatBot/plugins/ChatBotApi/txbot.py
src/plugins/FuckMsg/__init__.py
src/plugins/FuckMsg/config.py
src/plugins/FuckMsg/plugins/__init__.py
src/plugins/FuckMsg/plugins/fuckmsg.py
src/plugins/FuckMsg/plugins/fuckmsgs.py
elfchatbot-0.0.1.dist-info/LICENSE
elfchatbot-0.0.1.dist-info/METADATA
elfchatbot-0.0.1.dist-info/WHEEL
elfchatbot-0.0.1.dist-info/top_level.txt
elfchatbot-0.0.1.dist-info/RECORD
