Metadata-Version: 2.1
Name: elfchatbot
Version: 0.0.1
Summary: 闲聊QQ机器人，也就是人工智障
Home-page: https://github.com/Quan666/ELFChatBot
Author: Quan666
Author-email: i@oy.mk
License: UNKNOWN
Platform: UNKNOWN
Classifier: Programming Language :: Python :: 3
Classifier: License :: OSI Approved :: GNU General Public License v3 (GPLv3)
Classifier: Operating System :: OS Independent
